{
    "success": {
        "code": 200,
        "message": "successfully",
        "sucess_login": {
            "message": "Logged in Successfully"
        },
        "sucess_data": {
            "message": "Success retrieving  data"
        },
        "success_creating_data": {
            "message": "Success creating new data"
        },
        "success_updating_data": {
            "message": "Success updating new data"
        },
        "success_deleting_data": {
            "message": "Success deleting data"
        }
    },
    "trace": {
        "executing_query": {
            "message": "Data is executing"
        },
        "required_fields": {
            "message": "Check required fields"
        },
        "check_data_length": {
            "message": "Check payload length"
        }
    },
    "error": {
        "error_general": {
            "code": 1100,
            "message": "Error occured"
        },
        "error_notactive": {
            "code": 1105,
            "message": "You are temporary deactivated"
        },
        "error_no_data": {
            "code": 1101,
            "message": "No data found"
        },
        "error_missing_payload": {
            "code": 2100,
            "message": "Request payload is missing"
        },
        "error_invalid_payload": {
            "code": 2101,
            "message": "Request payload is invalid"
        },
        "error_invalid_input": {
            "code": 2102,
            "message": "Request inputs is/are invalid"
        },
        "error_no_user_found": {
            "code": 404,
            "message": "Could not find user!"
        },
        "error_unauthorized": {
            "code": 401,
            "message": "Authorization error"
        },
        "error_forbidden_access": {
            "code": 403,
            "message": "Access forbidden!"
        },
        "error_not_found": {
            "code": 404,
            "message": "Not found!"
        },
        "error_already_exists": {
            "code": 3100,
            "message": "Already exists!"
        },
        "error_no_data_created": {
            "code": 1102,
            "message": "No data was created"
        },
        "error_no_data_updated": {
            "code": 1103,
            "message": "No data was updated"
        },
        "error_no_data_delete": {
            "code": 1104,
            "message": "No data deleted"
        },
        "error_delete_public": {
            "code": 1106,
            "message": "Public group is forbidden to be delete!"
        }
    }
}